m4b_tools/__init__.py
m4b_tools/cli.py
m4b_tools/combiner.py
m4b_tools/converter.py
m4b_tools/metadata.py
m4b_tools/splitter.py
m4b_tools/utils.py
m4b_tools-1.0.0.dist-info/METADATA
m4b_tools-1.0.0.dist-info/WHEEL
m4b_tools-1.0.0.dist-info/entry_points.txt
m4b_tools-1.0.0.dist-info/RECORD
