Metadata-Version: 2.4
Name: m4b-tools
Version: 1.0.0
Summary: Tools for converting audio files to M4B format, combining M4B files with chapters, and splitting M4B files by chapters
Project-URL: Homepage, https://github.com/elazarcoh/m4b-tools
Project-URL: Repository, https://github.com/elazarcoh/m4b-tools
Project-URL: Issues, https://github.com/elazarcoh/m4b-tools/issues
Author: M4B Tools Contributors
License: MIT
Classifier: Development Status :: 4 - Beta
Classifier: Environment :: Console
Classifier: Intended Audience :: End Users/Desktop
Classifier: License :: OSI Approved :: MIT License
Classifier: Operating System :: OS Independent
Classifier: Programming Language :: Python :: 3
Classifier: Programming Language :: Python :: 3.7
Classifier: Programming Language :: Python :: 3.8
Classifier: Programming Language :: Python :: 3.9
Classifier: Programming Language :: Python :: 3.10
Classifier: Programming Language :: Python :: 3.11
Classifier: Programming Language :: Python :: 3.12
Classifier: Topic :: Multimedia :: Sound/Audio :: Conversion
Requires-Python: >=3.7
Requires-Dist: typing-extensions>=3.7.4; python_version < '3.8'
Provides-Extra: progress
Requires-Dist: tqdm; extra == 'progress'
Provides-Extra: test
Requires-Dist: pytest-cov; extra == 'test'
Requires-Dist: pytest>=6.0; extra == 'test'
